gedcom/__init__.py
gedcom/helpers.py
gedcom/parser.py
gedcom/tags.py
gedcom/element/__init__.py
gedcom/element/element.py
gedcom/element/family.py
gedcom/element/file.py
gedcom/element/individual.py
gedcom/element/object.py
gedcom/element/root.py
tests/element/__init__.py
tests/element/test_element.py
tests/element/test_family.py
tests/element/test_file.py
tests/element/test_individual.py
tests/element/test_object.py
tests/element/test_root.py
python_gedcom-1.0.0.dist-info/LICENSE.txt
python_gedcom-1.0.0.dist-info/METADATA
python_gedcom-1.0.0.dist-info/WHEEL
python_gedcom-1.0.0.dist-info/top_level.txt
python_gedcom-1.0.0.dist-info/RECORD
