Metadata-Version: 2.1
Name: python-gedcom
Version: 1.0.0
Summary: A Python module for parsing, analyzing, and manipulating GEDCOM files.
Home-page: https://github.com/nickreynke/python-gedcom
Author: Nicklas Reincke
Author-email: contact@reynke.com
License: GPLv2
Project-URL: Source, https://github.com/nickreynke/python-gedcom
Project-URL: Bug Reports, https://github.com/nickreynke/python-gedcom/issues
Keywords: python gedcom parser
Platform: UNKNOWN
Classifier: Development Status :: 5 - Production/Stable
Classifier: Intended Audience :: Developers
Classifier: Topic :: Sociology :: Genealogy
Classifier: License :: OSI Approved :: GNU General Public License v2 (GPLv2)
Classifier: Programming Language :: Python :: 2
Classifier: Programming Language :: Python :: 2.7
Classifier: Programming Language :: Python :: 3
Classifier: Programming Language :: Python :: 3.4
Classifier: Programming Language :: Python :: 3.5
Classifier: Programming Language :: Python :: 3.6
Provides-Extra: dev
Provides-Extra: test
